[{"vin":"honda2010a7","engine_status":"off","latitude":12.357663,"longitude":76.59698,"name":"honda","engine_rpm":"280","speed":"38","fuel_capacity":"6","fuel_consumption":"14","odometer":"276","engine_load":"62","engine_temp":"82"},{"vin":"honda2010a7","engine_status":"off","latitude":12.355058,"longitude":76.597423,"name":"honda","engine_rpm":"252","speed":"37","fuel_capacity":"6","fuel_consumption":"1","odometer":"272","engine_load":"36","engine_temp":"98"},{"vin":"honda2010a7","engine_status":"off","latitude":12.352555,"longitude":76.596991,"name":"honda","engine_rpm":"252","speed":"39","fuel_capacity":"2","fuel_consumption":"1","odometer":"285","engine_load":"49","engine_temp":"70"},{"vin":"honda2010a7","engine_status":"off","latitude":12.352047,"longitude":76.59691,"name":"honda","engine_rpm":"213","speed":"32","fuel_capacity":"6","fuel_consumption":"9","odometer":"236","engine_load":"29","engine_temp":"75"},{"vin":"honda2010a7","engine_status":"off","latitude":12.35748,"longitude":76.592953,"name":"honda","engine_rpm":"282","speed":"35","fuel_capacity":"11","fuel_consumption":"14","odometer":"236","engine_load":"36","engine_temp":"82"},{"vin":"honda2010a7","engine_status":"off","latitude":12.357663,"longitude":76.59698,"name":"honda","engine_rpm":"220","speed":"36","fuel_capacity":"5","fuel_consumption":"0","odometer":"251","engine_load":"56","engine_temp":"74"},{"vin":"honda2010a7","engine_status":"off","latitude":12.355058,"longitude":76.597423,"name":"honda","engine_rpm":"249","speed":"36","fuel_capacity":"14","fuel_consumption":"10","odometer":"260","engine_load":"38","engine_temp":"74"},{"vin":"honda2010a7","engine_status":"off","latitude":12.352555,"longitude":76.596991,"name":"honda","engine_rpm":"257","speed":"39","fuel_capacity":"6","fuel_consumption":"1","odometer":"266","engine_load":"24","engine_temp":"69"},{"vin":"honda2010a7","engine_status":"off","latitude":12.35748,"longitude":76.592953,"name":"honda","engine_rpm":"208","speed":"29","fuel_capacity":"4","fuel_consumption":"15","odometer":"28183434","engine_load":"58","engine_temp":"74"},{"vin":"honda2010a7","engine_status":"off","latitude":12.357663,"longitude":76.59698,"name":"honda","engine_rpm":"294","speed":"40","fuel_capacity":"7","fuel_consumption":"3","odometer":"23559043","engine_load":"74","engine_temp":"77"},{"vin":"honda2010a7","engine_status":"off","latitude":12.35748,"longitude":76.592953,"name":"honda","engine_rpm":"292","speed":"40","fuel_capacity":"9","fuel_consumption":"10","odometer":"2493913","engine_load":"23","engine_temp":"79"},{"vin":"honda2010a7","engine_status":"off","latitude":12.35748,"longitude":76.592953,"name":"honda","engine_rpm":"208","speed":"30","fuel_capacity":"8","fuel_consumption":"8","odometer":"3722784","engine_load":"74","engine_temp":"84"},{"vin":"honda2010a7","engine_status":"off","latitude":12.357663,"longitude":76.59698,"name":"honda","engine_rpm":"244","speed":"36","fuel_capacity":"5","fuel_consumption":"12","odometer":"1213597","engine_load":"57","engine_temp":"78"},{"vin":"honda2010a7","engine_status":"off","latitude":12.35748,"longitude":76.592953,"name":"honda","engine_rpm":"279","speed":"38","fuel_capacity":"4","fuel_consumption":"3","odometer":"1498062","engine_load":"70","engine_temp":"70"},{"vin":"honda2010a7","engine_status":"off","latitude":12.357663,"longitude":76.59698,"name":"honda","engine_rpm":"220","speed":"30","fuel_capacity":"15","fuel_consumption":"3","odometer":"4766520","engine_load":"76","engine_temp":"82"},{"vin":"honda2010a7","engine_status":"off","latitude":12.355058,"longitude":76.597423,"name":"honda","engine_rpm":"218","speed":"30","fuel_capacity":"7","fuel_consumption":"7","odometer":"4415154","engine_load":"41","engine_temp":"70"},{"vin":"honda2010a7","engine_status":"off","latitude":12.352555,"longitude":76.596991,"name":"honda","engine_rpm":"285","speed":"39","fuel_capacity":"7","fuel_consumption":"15","odometer":"5409670","engine_load":"72","engine_temp":"71"},{"vin":"honda2010a7","engine_status":"off","latitude":12.352047,"longitude":76.59691,"name":"honda","engine_rpm":"252","speed":"36","fuel_capacity":"12","fuel_consumption":"1","odometer":"4415342","engine_load":"41","engine_temp":"78"},{"vin":"honda2010a7","engine_status":"off","latitude":12.35748,"longitude":76.592953,"name":"honda","engine_rpm":"247","speed":"34","fuel_capacity":"0","fuel_consumption":"0","odometer":"4351003","engine_load":"50","engine_temp":"72"},{"vin":"honda2010a7","engine_status":"off","latitude":12.35748,"longitude":76.592953,"name":"honda","engine_rpm":"295","speed":"40","fuel_capacity":"9","fuel_consumption":"15","odometer":"815144","engine_load":"27","engine_temp":"80"},{"vin":"honda2010a7","engine_status":"off","latitude":12.357663,"longitude":76.59698,"name":"honda","engine_rpm":"251","speed":"36","fuel_capacity":"9","fuel_consumption":"7","odometer":"2042858","engine_load":"48","engine_temp":"91"},{"vin":"honda2010a7","engine_status":"off","latitude":12.355058,"longitude":76.597423,"name":"honda","engine_rpm":"254","speed":"35","fuel_capacity":"0","fuel_consumption":"0","odometer":"2791460","engine_load":"28","engine_temp":"97"},{"vin":"honda2010a7","engine_status":"off","latitude":12.352555,"longitude":76.596991,"name":"honda","engine_rpm":"212","speed":"30","fuel_capacity":"9","fuel_consumption":"11","odometer":"718934","engine_load":"25","engine_temp":"97"},{"vin":"honda2010a7","engine_status":"off","latitude":12.352047,"longitude":76.59691,"name":"honda","engine_rpm":"264","speed":"36","fuel_capacity":"7","fuel_consumption":"3","odometer":"5610401","engine_load":"78","engine_temp":"72"},{"vin":"honda2010a7","engine_status":"off","latitude":12.351419,"longitude":76.596803,"name":"honda","engine_rpm":"249","speed":"36","fuel_capacity":"10","fuel_consumption":"2","odometer":"2364344","engine_load":"39","engine_temp":"99"},{"vin":"honda2010a7","engine_status":"off","latitude":12.35096,"longitude":76.596771,"name":"honda","engine_rpm":"202","speed":"28","fuel_capacity":"8","fuel_consumption":"14","odometer":"1420787","engine_load":"42","engine_temp":"86"},{"vin":"honda2010a7","engine_status":"off","latitude":12.350672,"longitude":76.59675,"name":"honda","engine_rpm":"290","speed":"40","fuel_capacity":"13","fuel_consumption":"1","odometer":"6556320","engine_load":"24","engine_temp":"88"},{"vin":"honda2010a7","engine_status":"off","latitude":12.35748,"longitude":76.592953,"name":"honda","engine_rpm":"266","speed":"36","fuel_capacity":"3","fuel_consumption":"1","odometer":"1804118","engine_load":"80","engine_temp":"73"},{"vin":"honda2010a7","engine_status":"off","latitude":12.357663,"longitude":76.59698,"name":"honda","engine_rpm":"253","speed":"36","fuel_capacity":"11","fuel_consumption":"7","odometer":"3946678","engine_load":"45","engine_temp":"96"},{"vin":"honda2010a7","engine_status":"off","latitude":12.35748,"longitude":76.592953,"name":"honda","engine_rpm":"285","speed":"39","fuel_capacity":"3","fuel_consumption":"14","odometer":"8899780","engine_load":"37","engine_temp":"98"},{"vin":"honda2010a7","engine_status":"off","latitude":12.357663,"longitude":76.59698,"name":"honda","engine_rpm":"281","speed":"39","fuel_capacity":"9","fuel_consumption":"15","odometer":"1514095","engine_load":"27","engine_temp":"82"},{"vin":"honda2010a7","engine_status":"off","latitude":12.35748,"longitude":76.592953,"name":"honda","engine_rpm":"210","speed":"29","fuel_capacity":"1","fuel_consumption":"11","odometer":"5067489","engine_load":"54","engine_temp":"71"},{"vin":"honda2010a7","engine_status":"off","latitude":12.357663,"longitude":76.59698,"name":"honda","engine_rpm":"216","speed":"29","fuel_capacity":"12","fuel_consumption":"15","odometer":"3855116","engine_load":"29","engine_temp":"86"},{"vin":"honda2010a7","engine_status":"off","latitude":12.35748,"longitude":76.592953,"name":"honda","engine_rpm":"227","speed":"33","fuel_capacity":"13","fuel_consumption":"13","odometer":"3881087","engine_load":"57","engine_temp":"85"},{"vin":"honda2010a7","engine_status":"off","latitude":12.357663,"longitude":76.59698,"name":"honda","engine_rpm":"221","speed":"30","fuel_capacity":"11","fuel_consumption":"13","odometer":"3247639","engine_load":"54","engine_temp":"88"},{"vin":"honda2010a7","engine_status":"off","latitude":12.355058,"longitude":76.597423,"name":"honda","engine_rpm":"222","speed":"30","fuel_capacity":"15","fuel_consumption":"4","odometer":"4684377","engine_load":"55","engine_temp":"84"},{"vin":"honda2010a7","engine_status":"off","latitude":12.352555,"longitude":76.596991,"name":"honda","engine_rpm":"205","speed":"28","fuel_capacity":"0","fuel_consumption":"12","odometer":"540708","engine_load":"54","engine_temp":"93"},{"vin":"honda2010a7","engine_status":"off","latitude":12.352047,"longitude":76.59691,"name":"honda","engine_rpm":"221","speed":"31","fuel_capacity":"8","fuel_consumption":"9","odometer":"6130959","engine_load":"43","engine_temp":"83"},{"vin":"honda2010a7","engine_status":"off","latitude":12.351419,"longitude":76.596803,"name":"honda","engine_rpm":"245","speed":"34","fuel_capacity":"12","fuel_consumption":"9","odometer":"4708116","engine_load":"58","engine_temp":"85"},{"vin":"honda2010a7","engine_status":"off","latitude":12.35748,"longitude":76.592953,"name":"honda","engine_rpm":"274","speed":"38","fuel_capacity":"5","fuel_consumption":"6","odometer":"3923241","engine_load":"48","engine_temp":"90"},{"vin":"honda2010a7","engine_status":"off","latitude":12.357663,"longitude":76.59698,"name":"honda","engine_rpm":"257","speed":"36","fuel_capacity":"10","fuel_consumption":"10","odometer":"3369948","engine_load":"70","engine_temp":"69"},{"vin":"honda2010a7","engine_status":"off","latitude":12.355058,"longitude":76.597423,"name":"honda","engine_rpm":"215","speed":"31","fuel_capacity":"9","fuel_consumption":"8","odometer":"2302091","engine_load":"55","engine_temp":"84"},{"vin":"honda2010a7","engine_status":"off","latitude":12.352555,"longitude":76.596991,"name":"honda","engine_rpm":"271","speed":"40","fuel_capacity":"10","fuel_consumption":"1","odometer":"3233572","engine_load":"73","engine_temp":"76"},{"vin":"honda2010a7","engine_status":"off","latitude":12.35748,"longitude":76.592953,"name":"honda","engine_rpm":"263","speed":"39","fuel_capacity":"10","fuel_consumption":"2","odometer":"1288279","engine_load":"56","engine_temp":"71"},{"vin":"honda2010a7","engine_status":"off","latitude":12.357663,"longitude":76.59698,"name":"honda","engine_rpm":"254","speed":"37","fuel_capacity":"14","fuel_consumption":"5","odometer":"5311749","engine_load":"23","engine_temp":"96"},{"vin":"honda2010a7","engine_status":"off","latitude":12.355058,"longitude":76.597423,"name":"honda","engine_rpm":"293","speed":"40","fuel_capacity":"4","fuel_consumption":"13","odometer":"8390582","engine_load":"51","engine_temp":"78"},{"vin":"honda2010a7","engine_status":"off","latitude":12.352555,"longitude":76.596991,"name":"honda","engine_rpm":"226","speed":"33","fuel_capacity":"6","fuel_consumption":"12","odometer":"5151986","engine_load":"29","engine_temp":"97"},{"vin":"honda2010a7","engine_status":"off","latitude":12.352047,"longitude":76.59691,"name":"honda","engine_rpm":"272","speed":"40","fuel_capacity":"9","fuel_consumption":"0","odometer":"2664729","engine_load":"71","engine_temp":"79"},{"vin":"honda2010a7","engine_status":"off","latitude":12.351419,"longitude":76.596803,"name":"honda","engine_rpm":"255","speed":"37","fuel_capacity":"12","fuel_consumption":"10","odometer":"6962086","engine_load":"57","engine_temp":"76"},{"vin":"honda2010a7","engine_status":"off","latitude":12.35096,"longitude":76.596771,"name":"honda","engine_rpm":"286","speed":"41","fuel_capacity":"7","fuel_consumption":"10","odometer":"3534685","engine_load":"23","engine_temp":"89"},{"vin":"honda2010a7","engine_status":"off","latitude":12.350672,"longitude":76.59675,"name":"honda","engine_rpm":"225","speed":"33","fuel_capacity":"11","fuel_consumption":"9","odometer":"6994350","engine_load":"24","engine_temp":"76"},{"vin":"honda2010a7","engine_status":"off","latitude":12.350024,"longitude":76.5967,"name":"honda","engine_rpm":"231","speed":"33","fuel_capacity":"7","fuel_consumption":"2","odometer":"3303198","engine_load":"76","engine_temp":"72"},{"vin":"honda2010a7","engine_status":"off","latitude":12.35748,"longitude":76.592953,"name":"honda","engine_rpm":"208","speed":"30","fuel_capacity":"1","fuel_consumption":"0","odometer":"1253990","engine_load":"71","engine_temp":"84"},{"vin":"honda2010a7","engine_status":"off","latitude":12.357663,"longitude":76.59698,"name":"honda","engine_rpm":"279","speed":"38","fuel_capacity":"10","fuel_consumption":"2","odometer":"7989667","engine_load":"60","engine_temp":"73"},{"vin":"honda2010a7","engine_status":"off","latitude":12.355058,"longitude":76.597423,"name":"honda","engine_rpm":"281","speed":"39","fuel_capacity":"0","fuel_consumption":"4","odometer":"2684078","engine_load":"30","engine_temp":"83"},{"vin":"honda2010a7","engine_status":"off","latitude":12.352555,"longitude":76.596991,"name":"honda","engine_rpm":"278","speed":"39","fuel_capacity":"6","fuel_consumption":"5","odometer":"680877","engine_load":"32","engine_temp":"92"},{"vin":"honda2010a7","engine_status":"off","latitude":12.352047,"longitude":76.59691,"name":"honda","engine_rpm":"203","speed":"28","fuel_capacity":"14","fuel_consumption":"6","odometer":"2141731","engine_load":"58","engine_temp":"72"},{"vin":"honda2010a7","engine_status":"off","latitude":12.351419,"longitude":76.596803,"name":"honda","engine_rpm":"267","speed":"39","fuel_capacity":"10","fuel_consumption":"7","odometer":"3465862","engine_load":"42","engine_temp":"82"},{"vin":"honda2010a7","engine_status":"off","latitude":12.35096,"longitude":76.596771,"name":"honda","engine_rpm":"284","speed":"39","fuel_capacity":"8","fuel_consumption":"4","odometer":"1878046","engine_load":"39","engine_temp":"72"},{"vin":"honda2010a7","engine_status":"off","latitude":12.350672,"longitude":76.59675,"name":"honda","engine_rpm":"278","speed":"38","fuel_capacity":"3","fuel_consumption":"14","odometer":"1857573","engine_load":"56","engine_temp":"84"},{"vin":"honda2010a7","engine_status":"off","latitude":12.350024,"longitude":76.5967,"name":"honda","engine_rpm":"262","speed":"38","fuel_capacity":"15","fuel_consumption":"14","odometer":"4407919","engine_load":"62","engine_temp":"81"},{"vin":"honda2010a7","engine_status":"off","latitude":12.349253,"longitude":76.596632,"name":"honda","engine_rpm":"206","speed":"28","fuel_capacity":"1","fuel_consumption":"14","odometer":"1738705","engine_load":"48","engine_temp":"97"},{"vin":"honda2010a7","engine_status":"off","latitude":12.35748,"longitude":76.592953,"name":"honda","engine_rpm":"260","speed":"37","fuel_capacity":"10","fuel_consumption":"13","odometer":"4531020","engine_load":"46","engine_temp":"84"},{"vin":"honda2010a7","engine_status":"off","latitude":12.357663,"longitude":76.59698,"name":"honda","engine_rpm":"213","speed":"29","fuel_capacity":"6","fuel_consumption":"4","odometer":"1086163","engine_load":"70","engine_temp":"71"},{"vin":"honda2010a7","engine_status":"off","latitude":12.355058,"longitude":76.597423,"name":"honda","engine_rpm":"276","speed":"40","fuel_capacity":"4","fuel_consumption":"4","odometer":"5927817","engine_load":"43","engine_temp":"97"},{"vin":"honda2010a7","engine_status":"off","latitude":12.352555,"longitude":76.596991,"name":"honda","engine_rpm":"294","speed":"42","fuel_capacity":"4","fuel_consumption":"2","odometer":"2791635","engine_load":"35","engine_temp":"90"},{"vin":"honda2010a7","engine_status":"off","latitude":12.352047,"longitude":76.59691,"name":"honda","engine_rpm":"252","speed":"36","fuel_capacity":"10","fuel_consumption":"3","odometer":"3845620","engine_load":"36","engine_temp":"94"},{"vin":"honda2010a7","engine_status":"off","latitude":12.35748,"longitude":76.592953,"name":"honda","engine_rpm":"239","speed":"35","fuel_capacity":"6","fuel_consumption":"1","odometer":"1707296","engine_load":"47","engine_temp":"98"},{"vin":"honda2010a7","engine_status":"off","latitude":12.357663,"longitude":76.59698,"name":"honda","engine_rpm":"206","speed":"29","fuel_capacity":"9","fuel_consumption":"2","odometer":"5439924","engine_load":"46","engine_temp":"94"},{"vin":"honda2010a7","engine_status":"off","latitude":12.355058,"longitude":76.597423,"name":"honda","engine_rpm":"206","speed":"29","fuel_capacity":"7","fuel_consumption":"11","odometer":"3151404","engine_load":"40","engine_temp":"92"},{"vin":"honda2010a7","engine_status":"off","latitude":12.352555,"longitude":76.596991,"name":"honda","engine_rpm":"273","speed":"40","fuel_capacity":"1","fuel_consumption":"12","odometer":"1577284","engine_load":"60","engine_temp":"76"},{"vin":"honda2010a7","engine_status":"off","latitude":12.352047,"longitude":76.59691,"name":"honda","engine_rpm":"217","speed":"31","fuel_capacity":"5","fuel_consumption":"6","odometer":"1563085","engine_load":"20","engine_temp":"92"},{"vin":"honda2010a7","engine_status":"off","latitude":12.351419,"longitude":76.596803,"name":"honda","engine_rpm":"221","speed":"32","fuel_capacity":"4","fuel_consumption":"0","odometer":"1154716","engine_load":"58","engine_temp":"89"}]